SecureBase/Keccak.py
SecureBase/__init__.py
SecureBase-1.2.dist-info/METADATA
SecureBase-1.2.dist-info/WHEEL
SecureBase-1.2.dist-info/top_level.txt
SecureBase-1.2.dist-info/RECORD
