Metadata-Version: 2.2
Name: SecureBase
Version: 1.2
Summary: SecureBase Python Library
Home-page: https://beytullahakyuz.gitbook.io/securebase
Author: beytullahakyuz
Author-email: beytullahakyuz@hotmail.com.tr
License: MIT
Classifier: Programming Language :: Python :: 3
Classifier: License :: OSI Approved :: MIT License
Requires-Python: >=3.0
Dynamic: author
Dynamic: author-email
Dynamic: classifier
Dynamic: description
Dynamic: description-content-type
Dynamic: home-page
Dynamic: license
Dynamic: requires-python
Dynamic: summary
